unixreg/__init__.py
unixreg/constants.py
unixreg/functions.py
unixreg/key.py
unixreg-0.1.2.dist-info/LICENSE
unixreg-0.1.2.dist-info/METADATA
unixreg-0.1.2.dist-info/WHEEL
unixreg-0.1.2.dist-info/top_level.txt
unixreg-0.1.2.dist-info/RECORD
