Metadata-Version: 2.1
Name: unixreg
Version: 0.1.2
Summary: winreg implementation for non NT systems
Home-page: https://github.com/Jan200101/unixreg
Author: Jan Drögehoff
Author-email: jandroegehoff@gmail.com
License: MIT
Platform: UNKNOWN
Classifier: Development Status :: 3 - Alpha
Classifier: Programming Language :: Python :: 3
Classifier: License :: OSI Approved :: MIT License
Classifier: Operating System :: POSIX
Classifier: Operating System :: POSIX :: BSD
Classifier: Operating System :: POSIX :: Linux
Classifier: Topic :: Software Development :: Libraries :: Python Modules
Classifier: Typing :: Typed
Requires-Python: >=3.6
License-File: LICENSE
Requires-Dist: pytest
Requires-Dist: pylint
Requires-Dist: tox
